{
  "poster": {
    "subjects": [
      "movie scene dramatic",
      "event announcement",
      "concert performance",
      "theatrical production",
      "sports event",
      "festival celebration",
      "product launch",
      "motivational quote",
      "travel destination",
      "political campaign",
      "art exhibition",
      "educational infographic"
    ],
    "types": [
      "movie poster",
      "concert poster",
      "event flyer",
      "promotional poster",
      "vintage style poster",
      "minimalist poster",
      "typographic poster",
      "illustrated poster"
    ],
    "compositions": [
      "headline prominent",
      "key visual centered",
      "date and venue space",
      "call to action clear",
      "vertical format",
      "eye-catching layout",
      "information hierarchy"
    ],
    "elements": [
      "bold typography",
      "striking imagery",
      "brand colors",
      "clear messaging",
      "emotional impact",
      "memorable visual",
      "scannable layout"
    ],
    "styles": [
      "commercial poster design",
      "event marketing",
      "movie poster aesthetic",
      "promotional graphics",
      "advertising poster",
      "highly detailed realistic",
      "artistic stylized",
      "cinematic movie quality",
      "fine art gallery",
      "concept art professional"
    ]
  }


