{
  "name": "Urban Fantasy",
  "description": "Magic in modern city settings",
  "subjects": [
    "modern witch",
    "vampire detective",
    "werewolf biker",
    "fae in disguise",
    "urban mage",
    "demon bartender",
    "ghost hunter",
    "supernatural investigator"
  ],
  "environments": [
    "neon-lit alley with magic",
    "hidden magical shop",
    "supernatural nightclub",
    "haunted subway",
    "rooftop ritual",
    "modern apartment with artifacts",
    "city park at midnight",
    "underground magical market"
  ],
  "lighting": [
    "neon and magic glow",
    "streetlight shadows",
    "moonlit urban",
    "magical ambient",
    "club lighting with spells",
    "mysterious urban night"
  ],
  "styles": [
    "urban fantasy art",
    "modern magic",
    "contemporary supernatural",
    "city magic aesthetic",
    "Dresden Files inspired",
    "supernatural noir"
  ],
  "effects": [
    "magic in modern setting",
    "glowing runes on concrete",
    "supernatural creatures hiding",
    "spell effects",
    "glamour magic",
    "portal in alley"
  ],
  "shot_types": [
    "noir portrait",
    "urban action",
    "city backdrop",
    "mysterious medium shot",
    "dramatic confrontation",
    "supernatural reveal"
  ]
}






