{
    "tempera": {
        "composition_types": [
            "religious icon",
            "altarpiece panel",
            "devotional image",
            "portrait panel",
            "narrative scene",
            "symbolic composition",
            "gold ground painting",
            "manuscript illumination",
            "decorative panel",
            "triptych wing",
            "predella scene",
            "Madonna and Child",
            "saint portrait",
            "mythological scene",
            "allegorical panel"
        ],
        "subjects": [
            "sacred figure",
            "Madonna image",
            "Christ portrait",
            "saint icon",
            "biblical scene",
            "devotional subject",
            "noble portrait",
            "mythological figure",
            "allegorical scene",
            "religious narrative"
        ],
        "techniques": [
            "egg yolk binder",
            "layered application",
            "hatching strokes",
            "gold leaf gilding",
            "gesso preparation",
            "panel construction",
            "pigment grinding",
            "glaze building",
            "fine brushwork",
            "quick drying layers"
        ],
        "characteristics": [
            "matte finish",
            "luminous color",
            "fine detail",
            "quick drying",
            "permanent bond",
            "archival quality",
            "rich pigment",
            "smooth surface",
            "precise edges",
            "jewel-like color"
        ],
        "traditions": [
            "Byzantine icon",
            "Italian Gothic",
            "Early Renaissance",
            "Northern European",
            "Russian Orthodox",
            "Egyptian Fayum",
            "Medieval manuscript",
            "American regionalism",
            "contemporary revival",
            "modern technique"
        ],
        "moods": [
            "sacred devotion",
            "medieval beauty",
            "spiritual presence",
            "golden radiance",
            "timeless tradition",
            "refined elegance",
            "religious reverence",
            "historical depth",
            "artistic heritage",
            "luminous sanctity"
        ]
    }
}






