{
  "new_year": {
    "subjects": [
      "spectacular fireworks display",
      "champagne glasses toasting",
      "midnight countdown clock",
      "New Year's Eve party celebration",
      "confetti and streamers explosion",
      "ball drop Times Square style",
      "sparklers being held",
      "party crowd cheering",
      "2024 to 2025 transition",
      "celebration with balloons",
      "New Year's resolution list",
      "couples kissing at midnight"
    ],
    "environments": [
      "city skyline at midnight",
      "Times Square celebration",
      "rooftop party",
      "elegant ballroom gala",
      "harbor with fireworks",
      "outdoor street festival",
      "luxury penthouse party",
      "famous landmarks celebration"
    ],
    "lighting": [
      "brilliant firework explosions",
      "city lights at night",
      "sparkling chandelier",
      "disco ball reflections",
      "neon countdown display",
      "golden sparkler glow"
    ],
    "colors": [
      "gold and silver glamour",
      "black and gold elegant",
      "multicolor fireworks",
      "champagne gold",
      "sparkling metallic"
    ],
    "elements": [
      "fireworks bursting",
      "confetti falling",
      "party streamers",
      "champagne bubbles",
      "glitter and sparkle",
      "party hats and horns",
      "countdown numbers",
      "balloons",
      "clock striking twelve"
    ],
    "moods": [
      "celebratory and joyful",
      "hopeful and optimistic",
      "glamorous and festive",
      "exciting and energetic",
      "magical midnight moment"
    ]
  }
}

